pythonmacess/__init__.py
pythonmacess/__main__.py
pythonmacess/lib.py
pythonmacess-0.0.1.dist-info/LICENSE
pythonmacess-0.0.1.dist-info/METADATA
pythonmacess-0.0.1.dist-info/WHEEL
pythonmacess-0.0.1.dist-info/top_level.txt
pythonmacess-0.0.1.dist-info/RECORD
