Metadata-Version: 2.1
Name: pythonmacess
Version: 0.0.1
Summary: `python -m` acesss
Home-page: https://github.com/FarAway6834/pythonmacess
Author: du7ec
Author-email: dutec6834@gmail.com
Keywords: python,m,-m,acesss,pythonmacess
Classifier: Programming Language :: Python :: 3.0
Classifier: Programming Language :: Python :: 3.1
Classifier: Programming Language :: Python :: 3.2
Classifier: Programming Language :: Python :: 3.3
Classifier: Programming Language :: Python :: 3.4
Classifier: Programming Language :: Python :: 3.5
Classifier: Programming Language :: Python :: 3.6
Classifier: Programming Language :: Python :: 3.7
Classifier: Programming Language :: Python :: 3.8
Classifier: Programming Language :: Python :: 3.9
Classifier: Programming Language :: Python :: 3.10
Classifier: Programming Language :: Python :: 3.11
Classifier: Programming Language :: Python :: 3.12
Classifier: Programming Language :: Python :: 3.13
Classifier: Programming Language :: Python :: 3.14
Requires-Python: >=3.0
License-File: LICENSE
Requires-Dist: xxpop
